LICENSE
README.md
setup.py
aeronet_learn.egg-info/PKG-INFO
aeronet_learn.egg-info/SOURCES.txt
aeronet_learn.egg-info/dependency_links.txt
aeronet_learn.egg-info/requires.txt
aeronet_learn.egg-info/top_level.txt
nn/__init__.py
nn/activations/__init__.py
nn/activations/activation.py
nn/activations/leaky_relu.py
nn/activations/relu.py
nn/activations/sigmoid.py
nn/activations/softmax.py
nn/activations/tanh.py
nn/data_processing/__init__.py
nn/data_processing/file_io.py
nn/data_processing/image_utils.py
nn/initializers/__init__.py
nn/initializers/initializer.py
nn/initializers/normal.py
nn/initializers/uniform.py
nn/initializers/xavier.py
nn/initializers/zero.py
nn/layers/__init__.py
nn/layers/convolutional.py
nn/layers/dense.py
nn/layers/dropout.py
nn/layers/flatten.py
nn/layers/layer.py
nn/layers/layer_properties.py
nn/layers/maxpooling2d.py
nn/layers/reshape.py
nn/losses/__init__.py
nn/losses/binary_cross_entropy.py
nn/losses/categorical_cross_entropy.py
nn/losses/mean_squared_error.py
nn/network/__init__.py
nn/network/network.py
nn/network/training_set.py
nn/optimizers/__init__.py
nn/optimizers/momentum_sgd.py
nn/optimizers/optimizer.py
nn/optimizers/sgd.py