Metadata-Version: 2.1
Name: aeronet-learn
Version: 1.0.3
Summary: AeroNet is an educational neural network library. It is written entirely using python, numpy, and scipy.
Home-page: https://github.com/Logon27/AeroNet
Author: Logan Zehm
Author-email: logondz27@gmail.com
License: LICENSE
Platform: UNKNOWN
Classifier: Programming Language :: Python :: 3.10
Classifier: Operating System :: OS Independent
License-File: LICENSE
